pyforcedirectedlayout/Configuration.py
pyforcedirectedlayout/ForceDirectedLayout.py
pyforcedirectedlayout/LayoutTypes.py
pyforcedirectedlayout/Node.py
pyforcedirectedlayout/NodeLayoutInformation.py
pyforcedirectedlayout/Point.py
pyforcedirectedlayout/Rectangle.py
pyforcedirectedlayout/Size.py
pyforcedirectedlayout/Vector.py
pyforcedirectedlayout/__init__.py
pyforcedirectedlayout/_version.py
pyforcedirectedlayout/py.typed
pyforcedirectedlayout-0.80.6.dist-info/LICENSE
pyforcedirectedlayout-0.80.6.dist-info/METADATA
pyforcedirectedlayout-0.80.6.dist-info/WHEEL
pyforcedirectedlayout-0.80.6.dist-info/top_level.txt
pyforcedirectedlayout-0.80.6.dist-info/RECORD
