Metadata-Version: 2.1
Name: pyforcedirectedlayout
Version: 0.80.6
Summary: Python Implementation of a Force Directed Layout Algorithm
Author-email: "Humberto A. Sanchez II" <Humbert.A.Sanchez.II@gmail.com>
Maintainer-email: "Humberto A. Sanchez II" <Humbert.A.Sanchez.II@gmail.com>
License: GNU AFFERO GENERAL PUBLIC LICENSE
Project-URL: Repository, https://github.com/py-force-directed-layout
Keywords: layout,diagram,python
License-File: LICENSE
Requires-Dist: codeallybasic>=1.8.0
